README.rst
setup.py
multipledispatch2/__init__.py
multipledispatch2/conflict.py
multipledispatch2/core.py
multipledispatch2/dispatcher.py
multipledispatch2/utils.py
multipledispatch2.egg-info/PKG-INFO
multipledispatch2.egg-info/SOURCES.txt
multipledispatch2.egg-info/dependency_links.txt
multipledispatch2.egg-info/not-zip-safe
multipledispatch2.egg-info/top_level.txt
test/test.py