Metadata-Version: 1.0
Name: multipledispatch2
Version: 0.4.0
Summary: Multiple dispatch
Home-page: http://github.com/doomsplayer/multipledispatch2/
Author: Young Wu
Author-email: doomsplayer@gmail.com
License: BSD
Keywords: dispatch
Platform: UNKNOWN
